fixcompliance/__init__.py
fixcompliance/py.typed
fixcompliance/data/benchmark_template.json
fixcompliance/data/check_template.json
fixcompliance/data/benchmark/aws/aws_cis_1_5.json
fixcompliance/data/benchmark/aws/aws_cis_2_0.json
fixcompliance/data/benchmark/aws/aws_well_architected_framework_security_pillar.json
fixcompliance/data/benchmark/aws/iso27001.json
fixcompliance/data/benchmark/aws/nis-2.json
fixcompliance/data/benchmark/aws/waf_notes.md
fixcompliance/data/benchmark/azure/azure_cis_2_1.json
fixcompliance/data/checks/aws/aws_acm.json
fixcompliance/data/checks/aws/aws_apigateway.json
fixcompliance/data/checks/aws/aws_autoscaling.json
fixcompliance/data/checks/aws/aws_cloudformation.json
fixcompliance/data/checks/aws/aws_cloudfront.json
fixcompliance/data/checks/aws/aws_cloudtrail.json
fixcompliance/data/checks/aws/aws_cloudwatch.json
fixcompliance/data/checks/aws/aws_config.json
fixcompliance/data/checks/aws/aws_dms.json
fixcompliance/data/checks/aws/aws_dynamodb.json
fixcompliance/data/checks/aws/aws_ec2.json
fixcompliance/data/checks/aws/aws_ecr.json
fixcompliance/data/checks/aws/aws_ecs.json
fixcompliance/data/checks/aws/aws_efs.json
fixcompliance/data/checks/aws/aws_eks.json
fixcompliance/data/checks/aws/aws_elasticache.json
fixcompliance/data/checks/aws/aws_elb.json
fixcompliance/data/checks/aws/aws_elbv2.json
fixcompliance/data/checks/aws/aws_glacier.json
fixcompliance/data/checks/aws/aws_iam.json
fixcompliance/data/checks/aws/aws_kms.json
fixcompliance/data/checks/aws/aws_lambda.json
fixcompliance/data/checks/aws/aws_opensearch.json
fixcompliance/data/checks/aws/aws_organizations.json
fixcompliance/data/checks/aws/aws_rds.json
fixcompliance/data/checks/aws/aws_redshift.json
fixcompliance/data/checks/aws/aws_route53.json
fixcompliance/data/checks/aws/aws_s3.json
fixcompliance/data/checks/aws/aws_sagemaker.json
fixcompliance/data/checks/aws/aws_secretsmanager.json
fixcompliance/data/checks/aws/aws_sns.json
fixcompliance/data/checks/aws/aws_sqs.json
fixcompliance-0.4.36.dist-info/METADATA
fixcompliance-0.4.36.dist-info/WHEEL
fixcompliance-0.4.36.dist-info/top_level.txt
fixcompliance-0.4.36.dist-info/RECORD
